vlab_inf_common/__init__.py
vlab_inf_common/constants.py
vlab_inf_common/input_validators.py
vlab_inf_common/ssl_context.py
vlab_inf_common/views/__init__.py
vlab_inf_common/views/task_view.py
vlab_inf_common/vmware/__init__.py
vlab_inf_common/vmware/exceptions.py
vlab_inf_common/vmware/ova.py
vlab_inf_common/vmware/tasks.py
vlab_inf_common/vmware/vcenter.py
vlab_inf_common/vmware/virtual_machine.py
vlab_inf_common-2021.5.3.dist-info/METADATA
vlab_inf_common-2021.5.3.dist-info/RECORD
vlab_inf_common-2021.5.3.dist-info/WHEEL
vlab_inf_common-2021.5.3.dist-info/top_level.txt
