Metadata-Version: 2.1
Name: vlab-inf-common
Version: 2021.5.3
Summary: vLab common logic for working with virtual infrastructure
Home-page: UNKNOWN
Author: Nicholas Willhite, Kevin Broadware
Author-email: willnx84@gmail.com
License: UNKNOWN
Platform: UNKNOWN
Classifier: Development Status :: 4 - Beta
Classifier: Intended Audience :: Developers
Classifier: License :: OSI Approved :: Apache Software License
Classifier: Natural Language :: English
Classifier: Operating System :: POSIX :: Linux
Classifier: Programming Language :: Python :: 3.6
Requires-Dist: pyVmomi
Requires-Dist: vlab-api-common
Requires-Dist: pyOpenSSL
